{
  "epId": 4704,
  "name": "大型ボウシクラゲ",
  "iconUrl": "https://act-upload.hoyoverse.com/event-ugc-hoyowiki/2023/12/12/132746206/1ef525b101a31611b9fe2cc1b0a59aa8_7500491328607237491.png",
  "menuId": 14,
  "menuName": "チュートリアル",
  "version": 1702642555,
  "components": {
    "galleryCharacter": [
      {
        "key": "ページ　1/1",
        "img": "https://act-upload.hoyoverse.com/event-ugc-hoyowiki/2023/12/12/132746206/7c47aa12b046f6cd42fb5ad46e8a09a4_2809866455611940307.png",
        "imgDesc": [
          {
            "type": "RichText",
            "text": "<color=#ffffff>弾力性に優れており、キャラクターを吸い込んで空中に飛ばすことができる不思議なフォンテーヌの生き物。ボウシクラゲが進化した後の究極の姿だと言われています。</color>\n<color=#ffffff>マンマルタコ亜種のエネルギーによって、別の場所に</color> <color=#ffe14b>移動</color> <color=#ffffff>できます。</color>"
          }
        ]
      }
    ]
  }
}