{
  "epId": 239,
  "name": "Sospiro di Dvalin",
  "desc": "A bit of power taken from the whirlwinds evoked by the Dragon of the East.<br/>Beautiful and transparent, both trade winds and tornadoes will work in his name. The winds move as his companion, his voice, and his freedom.<br/>His enemies are the thousands who stand against the wind.",
  "iconUrl": "https://bbs.hoyolab.com/hoyowiki/picture/object/Dvalin's Sigh_icon.png",
  "menuId": 9,
  "menuName": "Risorse di Teyvat",
  "version": 1677158536,
  "components": {
    "customize": [
      {
        "type": "Heading",
        "level": 3,
        "text": "Dropped By"
      },
      {
        "type": "CustomEntry",
        "epId": 2217,
        "name": "Terrore alato",
        "desc": "<p>Uno dei Quattro Venti di Mondstadt: Dvalin, il Drago d'Oriente.</p><p>Dopo lunghi anni passati in un'oscurità sconfinata, anche la gemma più pura verrà offuscata dalla polvere, e perfino un nobile drago potrebbe diventare corrotto e consumato dall'odio.</p><p>Ma non dimenticare mai che la polvere può essere spazzata via, e il potere del dubbio e del veleno può essere infranto.</p><p>\"Vola liberamente nel cielo.\"</p><p>\"Proprio come facevi nei giorni in cui ci siamo incontrati, quando camminavo su questa terra e cantavo le canzoni del vento,\"</p><p>\"E tu volavi in alto, volgendo da lassù lo sguardo in basso verso il mondo.\"</p><p>\"Oggi il cielo non è più travolto da vento e neve. L'erba verde cresce su tutta la terra ed è bellissima.\"</p><p>\"Se anche tu potessi camminare sulla terra e sentire in lontananza i canti dei pastori e il suono che si disperde dei rintocchi del vento, se potessi assaporare il vino dolce come il miele, allora capiresti.\"</p><p>\"Come sarebbe stato meraviglioso se tu fossi come me, se avessi potuto ammirare la tua splendida e nobile forma mentre volavi nel cielo azzurro.\"</p><p>\"Allora sapresti che questo cielo e questa terra sono entrambi cose per cui vale la pena combattere.\"</p><p></p><p></p>",
        "iconUrl": "https://bbs.hoyolab.com/hoyowiki/picture/enemy/Stormterror_icon.png",
        "amount": 1,
        "displayStyle": "card"
      },
      {
        "type": "Heading",
        "level": 3,
        "text": "Character Talent Level-Up"
      },
      {
        "type": "RichText",
        "text": "<color=#ffffffd9>5-Star</color>"
      },
      {
        "type": "CustomEntry",
        "epId": 17,
        "name": "Viaggiatore/Viaggiatrice (Geo)",
        "desc": "<p><span style=\"color: rgba(255, 255, 255, 0.65)\">Un/a viaggiatore/rice di un altro mondo. Qualcuno gli/le ha strappato via il/la suo/a unico/a parente, e ora è costretto/a a intraprendere un viaggio alla ricerca dei Sette.</span></p>",
        "iconUrl": "https://upload-static.hoyoverse.com/hoyolab-wiki/2023/08/02/190184121/f00d18b57acb4aa37bf2fc39bf67ddd0_4899918200904566381.gif",
        "amount": 1,
        "displayStyle": "card"
      },
      {
        "type": "CustomEntry",
        "epId": 19,
        "name": "Viaggiatore/Viaggiatrice (Anemo)",
        "desc": "<p>Un/a viaggiatore/rice di un altro mondo. Qualcuno gli/le ha strappato via il/la suo/a unico/a parente, e ora è costretto/a a intraprendere un viaggio alla ricerca dei Sette.</p>",
        "iconUrl": "https://upload-static.hoyoverse.com/hoyolab-wiki/2023/08/02/190184121/f00d18b57acb4aa37bf2fc39bf67ddd0_7509376671980681559.gif",
        "amount": 1,
        "displayStyle": "card"
      },
      {
        "type": "CustomEntry",
        "epId": 20,
        "name": "Viaggiatore/Viaggiatrice",
        "desc": "<p><span style=\"color: rgba(255, 255, 255, 0.65)\">Un viaggiatore di un altro mondo. Qualcuno gli ha strappato via il suo unico parente, e ora è costretto/a a intraprendere un viaggio alla ricerca dei Sette.</span></p>",
        "iconUrl": "https://upload-static.hoyoverse.com/hoyolab-wiki/2023/08/02/190184121/f00d18b57acb4aa37bf2fc39bf67ddd0_885637890644803057.gif",
        "amount": 1,
        "displayStyle": "card"
      },
      {
        "type": "RichText",
        "text": "<color=#ffffffd9>4-Star</color>"
      },
      {
        "type": "CustomEntry",
        "epId": 45,
        "name": "Chongyun",
        "desc": "<p>Il giovane erede di una famiglia di esorcisti. Fa tutto il possibile per sopprimere la sua abbondanza di energia yang.</p>",
        "iconUrl": "https://bbs.hoyolab.com/hoyowiki/picture/character/Chongyun_icon.png",
        "amount": 1,
        "displayStyle": "card"
      },
      {
        "type": "CustomEntry",
        "epId": 11,
        "name": "Beidou",
        "desc": "<p><span style=\"color: rgba(255, 255, 255, 0.65)\">Capitana dell'equipaggio della Crux. Una donna diretta e indipendente.</span></p>",
        "iconUrl": "https://bbs.hoyolab.com/hoyowiki/picture/character/Beidou_icon.png",
        "amount": 1,
        "displayStyle": "card"
      },
      {
        "type": "CustomEntry",
        "epId": 14,
        "name": "Amber",
        "desc": "<p>Piena d'energia vitale, Amber è la migliore, nonché l'unica, Vigilante dei Cavalieri di Favonius</p>",
        "iconUrl": "https://bbs.hoyolab.com/hoyowiki/picture/character/Amber_icon.png",
        "amount": 1,
        "displayStyle": "card"
      },
      {
        "type": "Heading",
        "level": 3,
        "text": "Conversion"
      },
      {
        "type": "RichText",
        "text": "<color=#ffffff>Product</color>\n<color=#ffffff>Recipe</color>"
      },
      {
        "type": "CustomEntry",
        "epId": 239,
        "name": "Sospiro di Dvalin",
        "desc": "A bit of power taken from the whirlwinds evoked by the Dragon of the East.<br/>Beautiful and transparent, both trade winds and tornadoes will work in his name. The winds move as his companion, his voice, and his freedom.<br/>His enemies are the thousands who stand against the wind.",
        "iconUrl": "https://bbs.hoyolab.com/hoyowiki/picture/object/Dvalin's Sigh_icon.png",
        "amount": 1,
        "displayStyle": "text"
      },
      {
        "type": "CustomImage",
        "url": "https:/upload-static.hoyoverse.com/hoyolab-wiki/2023/01/02/35428890/4e6086b9dc09a363886dc42f8673f393_3795911938579587258.png",
        "alignment": "center"
      },
      {
        "type": "RichText",
        "text": "1x"
      },
      {
        "type": "CustomEntry",
        "epId": 238,
        "name": "Piuma di Dvalin",
        "desc": "A feather from the tail of the Dragon of the East.<br/>As a dragon's feather it has experienced more than a thousand years' worth of winds. One senses within it a yearning for freedom so strong that it could whip up a light breeze to rescue it from its current confines. Its former owner's recognition of you is what makes it content to stay in your hands.",
        "iconUrl": "https://bbs.hoyolab.com/hoyowiki/picture/object/Dvalin's Plume_icon.png",
        "amount": 1,
        "displayStyle": "text"
      },
      {
        "type": "RichText",
        "text": "1x"
      },
      {
        "type": "CustomEntry",
        "epId": 706,
        "name": "Solvente dei sogni",
        "desc": "<p>Un oggetto in grado di cambiare in qualsiasi forma necessaria i materiali per l'aumento di livello dei personaggi ottenuti dai ricordi e dalle prove. </p><p>La gente un tempo credeva che gli spiriti e i ricordi avessero una forma materiale. Se qualcuno sognava il paradiso per poi svegliarsi stringendo un fiore, allora quel fiore doveva essere stato creato da tale fantasia. Il solvente dei sogni dissolve ciò che si ottiene dal ricordo e lo trasforma in qualche altro sogno. In effetti, i colpi scambiati con i forti sono passi lungo la strada per diventare più forte a tua volta. </p>",
        "iconUrl": "https://bbs.hoyolab.com/hoyowiki/picture/object/Dream Solvent_icon.png",
        "amount": 1,
        "displayStyle": "text"
      },
      {
        "type": "CustomEntry",
        "epId": 239,
        "name": "Sospiro di Dvalin",
        "desc": "A bit of power taken from the whirlwinds evoked by the Dragon of the East.<br/>Beautiful and transparent, both trade winds and tornadoes will work in his name. The winds move as his companion, his voice, and his freedom.<br/>His enemies are the thousands who stand against the wind.",
        "iconUrl": "https://bbs.hoyolab.com/hoyowiki/picture/object/Dvalin's Sigh_icon.png",
        "amount": 1,
        "displayStyle": "text"
      },
      {
        "type": "CustomImage",
        "url": "https:/upload-static.hoyoverse.com/hoyolab-wiki/2023/01/02/35428890/4e6086b9dc09a363886dc42f8673f393_3795911938579587258.png",
        "alignment": "center"
      },
      {
        "type": "RichText",
        "text": "1x"
      },
      {
        "type": "CustomEntry",
        "epId": 237,
        "name": "Artiglio di Dvalin",
        "desc": "A claw from the Dragon of the East.<br/>It once contained the shadow dragon Durin's vile poison, having torn through the latter's flesh in battle. Thanks to your purification and healing, it is no longer toxic.",
        "iconUrl": "https://bbs.hoyolab.com/hoyowiki/picture/object/Dvalin's Claw_icon.png",
        "amount": 1,
        "displayStyle": "text"
      },
      {
        "type": "RichText",
        "text": "1x"
      },
      {
        "type": "CustomEntry",
        "epId": 706,
        "name": "Solvente dei sogni",
        "desc": "<p>Un oggetto in grado di cambiare in qualsiasi forma necessaria i materiali per l'aumento di livello dei personaggi ottenuti dai ricordi e dalle prove. </p><p>La gente un tempo credeva che gli spiriti e i ricordi avessero una forma materiale. Se qualcuno sognava il paradiso per poi svegliarsi stringendo un fiore, allora quel fiore doveva essere stato creato da tale fantasia. Il solvente dei sogni dissolve ciò che si ottiene dal ricordo e lo trasforma in qualche altro sogno. In effetti, i colpi scambiati con i forti sono passi lungo la strada per diventare più forte a tua volta. </p>",
        "iconUrl": "https://bbs.hoyolab.com/hoyowiki/picture/object/Dream Solvent_icon.png",
        "amount": 1,
        "displayStyle": "text"
      },
      {
        "type": "Heading",
        "level": 3,
        "text": "Related Materials"
      },
      {
        "type": "CustomEntry",
        "epId": 238,
        "name": "Piuma di Dvalin",
        "desc": "A feather from the tail of the Dragon of the East.<br/>As a dragon's feather it has experienced more than a thousand years' worth of winds. One senses within it a yearning for freedom so strong that it could whip up a light breeze to rescue it from its current confines. Its former owner's recognition of you is what makes it content to stay in your hands.",
        "iconUrl": "https://bbs.hoyolab.com/hoyowiki/picture/object/Dvalin's Plume_icon.png",
        "amount": 1,
        "displayStyle": "card"
      },
      {
        "type": "CustomEntry",
        "epId": 237,
        "name": "Artiglio di Dvalin",
        "desc": "A claw from the Dragon of the East.<br/>It once contained the shadow dragon Durin's vile poison, having torn through the latter's flesh in battle. Thanks to your purification and healing, it is no longer toxic.",
        "iconUrl": "https://bbs.hoyolab.com/hoyowiki/picture/object/Dvalin's Claw_icon.png",
        "amount": 1,
        "displayStyle": "card"
      }
    ],
    "baseInfo": [
      {
        "key": "Name",
        "value": [
          {
            "type": "RichText",
            "text": "Dvalin's Sigh"
          }
        ]
      },
      {
        "key": "Type",
        "value": [
          {
            "type": "RichText",
            "text": "Character Level-Up Material"
          }
        ]
      },
      {
        "key": "Source",
        "value": [
          {
            "type": "RichText",
            "text": "Lv. 70+ Stormterror Challenge Reward"
          }
        ]
      }
    ]
  }
}