{
  "epId": 1289,
  "name": "Dinh Thự Inazuma - Nhất Trí Một Lòng",
  "desc": "Bản vẽ chi tiết từng bước, ghi lại cách chế tạo \"Dinh Thự Inazuma - Nhất Trí Một Lòng\".<br/>Sau khi dùng có thể đến giao diện chế tạo để xem.",
  "iconUrl": "https://bbs.hoyolab.com/hoyowiki/picture/object/Inazuman Mansion: As One_icon.png",
  "filterValues": {
    "objectType": [
      "Bản Vẽ Đồ Trang Trí"
    ]
  },
  "menuId": 9,
  "menuName": "Sản vật Teyvat",
  "version": 0,
  "components": {
    "baseInfo": [
      {
        "key": "Tên",
        "value": [
          {
            "type": "RichText",
            "text": "Dinh Thự Inazuma - Nhất Trí Một Lòng"
          }
        ]
      },
      {
        "key": "Loại",
        "value": [
          {
            "type": "RichText",
            "text": "Bản Vẽ Đồ Trang Trí"
          }
        ]
      },
      {
        "key": "Công Dụng"
      },
      {
        "key": "Nguồn Gốc"
      }
    ]
  }
}