{
  "epId": 2717,
  "name": "Cây Kích Điện",
  "desc": "<p>Ma vật hình thành từ những dây leo khổng lồ hấp thụ dòng điện cao áp từ trong địa mạch.</p><p>Từ trong thân cây phóng ra nguồn điện vô tận, giống như đang bùng nổ cơn giận của mặt đất.</p><p>Từng có học giả của Học Phái Kshahrewar đề xuất, nếu xây dựng một mạng lưới đường điện phức tạp xung quanh Cây Kích Điện, sẽ có thể đưa điện năng trong đó truyền đến trong thành thị để sử dụng. Kế hoạch này đã bị học giả Học Phái Spantamad phản đối kịch liệt, vì điều này mà họ đã không tiếc hy sinh mười con Heo Nấm để chứng minh sự nguy hiểm của việc sử dụng điện.</p>",
  "iconUrl": "https://upload-static.hoyoverse.com/hoyolab-wiki/2022/09/24/27215281/12fc861bff06793fff2ebc2a470d4a0c_2639658379259793857.png",
  "menuId": 7,
  "menuName": "Kẻ Địch Và Ma Vật",
  "version": 1727032396,
  "components": {
    "baseInfo": [
      {
        "key": "Tên",
        "value": [
          {
            "type": "RichText",
            "text": "Cây Kích Điện"
          }
        ]
      },
      {
        "key": "Loại",
        "value": [
          {
            "type": "RichText",
            "text": "Ma Thú Đột Biến"
          }
        ]
      },
      {
        "key": "Giáo Trình",
        "value": [
          {
            "type": "RichText",
            "text": "Loại thực vật săn mồi tương tự như Cây Cấp Đông, Cây Nổ, sẽ kết thành một bộ phận nào đó giống như <color=#ffe14b>Hạt Nhân Nguyên Tố Lôi</color> ở phần rễ hoặc đài hoa. Khi bộ phận này xoay chuyển, nó sẽ thay đổi trạng thái, và tạo ra \"Nhụy Hoa Rực Rỡ\" và \"Nhụy Hoa Hư Vô\". Khi hai loại nhụy hoa cùng tồn tại sẽ <color=#ffe14b>thu hút lẫn nhau và khi va chạm sẽ gây nổ điện cực mạnh</color> . Nếu như phá hủy chúng thì sẽ dễ dàng chiến thắng hơn."
          }
        ]
      }
    ],
    "dropMaterial": [
      {
        "type": "CustomEntry",
        "epId": 757,
        "name": "Mora",
        "desc": "Tiền lưu hành trong đại lục. Là ngôn ngữ chung của thế giới.",
        "iconUrl": "https://bbs.hoyolab.com/hoyowiki/picture/object/Mora_icon.png"
      },
      {
        "type": "CustomEntry",
        "epId": 2715,
        "name": "Hạt Tụ Sấm",
        "desc": "<p>Lõi cây kích điện được bọc trong những chiếc lá sắc nhọn, tản ra nguyên tố Lôi khắp cơ thể.<br>Năng lượng cuồn cuộn sâu trong lòng đất đang muốn trút cơn thịnh nộ, thế là dây leo không may cũng bị nhiễm cơn cuồng bạo, vẫy cành uốn éo than khóc, không biết là muốn để người khác thử nếm trải nỗi đau khi bị sét đánh xuyên thân, hay là chật vật mong chờ cái kết không thể tránh khỏi.</p>",
        "iconUrl": "https://upload-static.hoyoverse.com/hoyolab-wiki/2022/09/02/148664880/48576af4b9400d3ca1bd645a5cbfca05_2044914215325402023.png"
      },
      {
        "type": "CustomEntry",
        "epId": 905,
        "name": "Vụn Tử Tinh Thắng Lợi",
        "desc": "Nguyên Liệu Đột Phá Nhân Vật",
        "iconUrl": "https://bbs.hoyolab.com/hoyowiki/picture/object/Vajrada Amethyst Sliver_icon.png"
      },
      {
        "type": "CustomEntry",
        "epId": 904,
        "name": "Mảnh Tử Tinh Thắng Lợi",
        "desc": "Nguyên liệu đột phá nhân vật.<br/>\"Thân thể này là thân thể tôn quý đặc biệt nhất trần thế.\"",
        "iconUrl": "https://bbs.hoyolab.com/hoyowiki/picture/object/Vajrada Amethyst Fragment_icon.png"
      },
      {
        "type": "CustomEntry",
        "epId": 903,
        "name": "Miếng Tử Tinh Thắng Lợi",
        "desc": "Nguyên liệu đột phá nhân vật.<br/>\"Thân thể này là thân thể tôn quý đặc biệt nhất trần thế.\"<br/>\"Nên nắm giữ đại quyền thiên hạ.\"",
        "iconUrl": "https://bbs.hoyolab.com/hoyowiki/picture/object/Vajrada Amethyst Chunk_icon.png"
      },
      {
        "type": "CustomEntry",
        "epId": 902,
        "name": "Tử Tinh Thắng Lợi",
        "desc": "Nguyên liệu đột phá nhân vật.<br/>\"Thân thể này là thân thể tôn quý đặc biệt nhất trần thế.\"<br/>\"Nên nắm giữ đại quyền thiên hạ.\"<br/>\"Thân thể này từng hứa một giấc mơ với thần dân, đó là sự \"vĩnh hằng\" ngàn năm vạn đời không thay đổi.\"",
        "iconUrl": "https://bbs.hoyolab.com/hoyowiki/picture/object/Vajrada Amethyst Gemstone_icon.png"
      },
      {
        "type": "CustomEntry",
        "epId": 2074,
        "name": "Giáo Quan",
        "iconUrl": "https://bbs.hoyolab.com/hoyowiki/picture/reliquary/Instructor/flower_of_life_icon.png"
      },
      {
        "type": "CustomEntry",
        "epId": 2080,
        "name": "Kẻ Lưu Đày",
        "iconUrl": "https://bbs.hoyolab.com/hoyowiki/picture/reliquary/The Exile/flower_of_life_icon.png"
      },
      {
        "type": "CustomEntry",
        "epId": 2089,
        "name": "Người Tế Lôi",
        "iconUrl": "https://bbs.hoyolab.com/hoyowiki/picture/reliquary/Prayers for Wisdom/circlet_of_logos_icon.png"
      },
      {
        "type": "CustomEntry",
        "epId": 2084,
        "name": "Thầy Thuốc",
        "iconUrl": "https://bbs.hoyolab.com/hoyowiki/picture/reliquary/Traveling Doctor/flower_of_life_icon.png"
      },
      {
        "type": "CustomEntry",
        "epId": 2095,
        "name": "Lễ Bế Mạc Của Giác Đấu Sĩ",
        "iconUrl": "https://bbs.hoyolab.com/hoyowiki/picture/reliquary/Gladiator's Finale/flower_of_life_icon.png"
      },
      {
        "type": "CustomEntry",
        "epId": 2081,
        "name": "Đoàn Hát Lang Thang Đại Lục",
        "iconUrl": "https://bbs.hoyolab.com/hoyowiki/picture/reliquary/Wanderer's Troupe/flower_of_life_icon.png"
      },
      {
        "type": "CustomEntry",
        "epId": 4927,
        "name": "EXP Yêu Thích",
        "desc": "<p>EXP Yêu Thích, có thể dùng tăng cấp Yêu Thích</p>",
        "iconUrl": "https://act-upload.hoyoverse.com/event-ugc-hoyowiki/2024/01/16/44749939/5bcd7c1bb38117a29ef80acde9931434_4514472129515766736.png"
      }
    ]
  }
}