{
  "epId": 8529,
  "name": "Thợ Săn Hoang Dã",
  "desc": "Bóng ma quẩn quanh nơi vùng đất giá lạnh hoang vu trong màn sương đen tối. Sự xuất hiện của chúng dường như dự báo trước một tai họa khủng khiếp hơn.<br>Dưới lớp băng giá nơi vùng đất mênh mông của phía bắc, chôn vùi các chiến binh vĩ đại của đất nước cổ xưa đã mất. Dù cho dấu vết tồn tại của họ đã bị xóa nhòa từ lâu, nhưng linh hồn anh dũng của dũng sĩ vẫn mãi bảo vệ vùng đất của vương quốc hoàng kim. Giờ đây, những linh hồn này đã thức tỉnh vì sự ô nhiễm của Vực Sâu, tất cả những kẻ dám xâm lược sẽ bị họ xem như con mồi.",
  "iconUrl": "https://act-webstatic.hoyoverse.com/event-static-hoyowiki-admin/2025/09/01/7f9c4baa3df6e8e5ef213f4a56e2b4c8_3642921521759104842.png",
  "menuId": 7,
  "menuName": "Kẻ Địch Và Ma Vật",
  "version": 0,
  "components": {
    "baseInfo": [
      {
        "key": "Tên",
        "value": [
          {
            "type": "RichText",
            "text": "Thợ Săn Hoang Dã"
          }
        ]
      }
    ],
    "galleryCharacter": [
      {
        "img": "https://act-webstatic.hoyoverse.com/event-static-hoyowiki-admin/2025/09/01/b180bcb7bb2925bee0981e3d8c60f2b2_3862356790746882042.png"
      }
    ]
  }
}