{
  "id": 3187,
  "name": "Razor",
  "desc": "<p>\"การ์ด ยาก\"</p><p>\"แต่ มีเพื่อน...\"</p>",
  "icon_url": "https://upload-static.hoyoverse.com/hoyolab-wiki/2022/12/02/144837601/31f1af14b97e8b36a6617bfa7f094abb_1112094279963317465.png",
  "modules": [
    {
      "id": "57",
      "name": null,
      "components": [
        {
          "component_id": "tcg",
          "data": {
            "cost_icon_type": "",
            "cost_icon_type_any": "",
            "header_imgs": [
              {
                "img_desc": "",
                "img_url": "https://upload-static.hoyoverse.com/hoyolab-wiki/2022/12/02/144837601/31f1af14b97e8b36a6617bfa7f094abb_1112094279963317465.png"
              },
              {
                "img_desc": "",
                "img_url": "https://upload-static.hoyoverse.com/hoyolab-wiki/2022/12/13/144837601/4aa24f7d71786379c80f61cffb0d3f56_2161408828883506953.gif"
              },
              {
                "img_desc": "",
                "img_url": "https://upload-static.hoyoverse.com/hoyolab-wiki/2022/12/13/144837601/afe1fe1cd77fac3d23e52afa1171d89c_3268104380370273293.png"
              }
            ],
            "hp": 10
          }
        }
      ]
    },
    {
      "id": "45",
      "name": "เนื้อเรื่อง",
      "components": [
        {
          "component_id": "story",
          "data": ""
        }
      ]
    },
    {
      "id": "46",
      "name": "ข้อมูลเพิ่มเติม",
      "components": [
        {
          "component_id": "textual_research",
          "data": ""
        }
      ]
    },
    {
      "id": "47",
      "name": "ค่าสถานะ",
      "components": [
        {
          "component_id": "baseInfo",
          "data": {
            "list": [
              {
                "item_values": [],
                "key": "ชื่อ",
                "string_values": [
                  "<p>Razor</p>"
                ]
              },
              {
                "item_values": [],
                "key": "ประเภทการ์ด",
                "string_values": [
                  "<p>การ์ดตัวละคร</p>"
                ]
              },
              {
                "item_values": [],
                "key": "พลังชีวิต",
                "string_values": [
                  "<p>10</p>"
                ]
              },
              {
                "item_values": [],
                "key": "พลังงาน",
                "string_values": [
                  "<p>3</p>"
                ]
              },
              {
                "item_values": [],
                "key": "ประเภทธาตุ",
                "string_values": [
                  "<p>ธาตุไฟฟ้า</p>"
                ]
              },
              {
                "item_values": [],
                "key": "อาวุธ",
                "string_values": [
                  "<p>ดาบใหญ่</p>"
                ]
              },
              {
                "item_values": [],
                "key": "ฝ่าย",
                "string_values": [
                  "<p>Mondstadt</p>"
                ]
              },
              {
                "isMaterial": true,
                "item_values": [
                  {
                    "amount": 0,
                    "ep_id": 3226,
                    "icon": "https://upload-static.hoyoverse.com/hoyolab-wiki/2022/12/02/144837601/c5cee39d24207d15ed0383b971e8afed_769971483047454770.png",
                    "menuId": 18,
                    "name": "Awakening"
                  }
                ],
                "key": "การ์ดที่เกี่ยวข้อง",
                "string_values": []
              },
              {
                "item_values": [],
                "key": "หาได้จาก",
                "string_values": [
                  "<p>ได้รับหลังจากเชิญ Razor ทำการดูเอลใน Cat's Tail และเอาชนะในระดับความยากฉันมิตร</p>"
                ]
              },
              {
                "isMaterial": true,
                "item_values": [
                  {
                    "amount": 0,
                    "ep_id": 48,
                    "icon": "https://bbs.hoyolab.com/hoyowiki/picture/character/Razor_icon.png",
                    "menuId": "",
                    "name": "Razor"
                  }
                ],
                "key": "ตัวละคร",
                "string_values": []
              }
            ]
          }
        }
      ]
    },
    {
      "id": "48",
      "name": "ความสามารถ",
      "components": [
        {
          "component_id": "talent",
          "data": {
            "list": [
              {
                "attributes": [],
                "desc": "<p><span style=\"color: rgb(255, 215, 128)\">โจมตีปกติ</span></p><p>จะสร้างความเสียหายกายภาพ 2 หน่วย</p>",
                "icon_url": "https://upload-static.hoyoverse.com/hoyolab-wiki/2022/12/13/144837601/10316b5178d5109d597f415d6e7903dc_5164657917705015025.png",
                "id": "talent94670",
                "key": "Steel Fang",
                "materials": [],
                "points": [
                  {
                    "point_count": 1,
                    "point_type": "electro"
                  },
                  {
                    "point_count": 2,
                    "point_type": "black"
                  }
                ],
                "talent_img": "",
                "title": "Steel Fang"
              },
              {
                "attributes": [],
                "desc": "<p><span style=\"color: rgb(255, 215, 128)\">สกิลธาตุ</span></p><p>จะสร้าง<span style=\"color: #FFACFF\">ความเสียหายไฟฟ้า</span> 3 หน่วย</p><p></p>",
                "icon_url": "https://upload-static.hoyoverse.com/hoyolab-wiki/2022/12/13/144837601/5a7f4821eca7816e8d923684ccee651c_1027706225455331937.png",
                "id": "talent3246",
                "key": "Claw and Thunder",
                "materials": [],
                "points": [
                  {
                    "point_count": 3,
                    "point_type": "electro"
                  }
                ],
                "talent_img": "",
                "title": "Claw and Thunder"
              },
              {
                "attributes": [],
                "desc": "<p><span style=\"color: rgb(255, 215, 128)\">ท่าไม้ตาย</span></p><p>สร้าง<span style=\"color: #FFACFF\">ความเสียหายไฟฟ้า</span> 5 หน่วย และตัวละครนี้จะได้รับ The Wolf Within</p>",
                "icon_url": "https://upload-static.hoyoverse.com/hoyolab-wiki/2022/12/13/144837601/898eb03f9942b7b7833a3c082a86fdef_632351789000058347.png",
                "id": "talent23378",
                "key": "Lightning Fang",
                "materials": [],
                "points": [
                  {
                    "point_count": 3,
                    "point_type": "electro"
                  },
                  {
                    "point_count": 3,
                    "point_type": "recharge"
                  }
                ],
                "talent_img": "",
                "title": "Lightning Fang"
              },
              {
                "attributes": [],
                "desc": "<p>การติดสถานะธาตุไฟฟ้าจะทำให้เกิดปฏิกิริยาธาตุดังนี้:</p><p>[<span style=\"color: rgb(255, 172, 255)\">Electro </span>+ <span style=\"color: rgb(255, 153, 153)\">Pyro</span>] <span style=\"color: #FFFFFF\">โอเวอร์โหลด: </span>ความเสียหายนี้ +2 และตัวเป้าหมายจะถูกบังคับให้เปลี่ยนไปใช้ตัวละครถัดไป</p><p>[<span style=\"color: rgb(255, 172, 255)\">Electro </span>+ <span style=\"color: rgb(153, 255, 255)\">Cryo</span>] <span style=\"color: #FFFFFF\">นำไฟฟ้า:</span> ความเสียหายนี้ +1 และสร้างความเสียหายทะลวง 1 หน่วย ให้กับตัวละครทั้งหมดของฝ่ายศัตรู (ยกเว้นเป้าหมาย)</p><p>[<span style=\"color: rgb(255, 172, 255)\">Electro </span>+ <span style=\"color: rgb(128, 192, 255)\">Hydro</span>] <span style=\"color: #FFFFFF\">ชาร์จไฟฟ้า:</span> ความเสียหายนี้ +1 และสร้างความเสียหายทะลวง 1 หน่วย ให้กับตัวละครทั้งหมดของฝ่ายศัตรู (ยกเว้นเป้าหมาย)</p><p>[<span style=\"color: rgb(255, 172, 255)\">Electro </span>+ <span style=\"color: rgb(153, 255, 136)\">Dendro</span>] <span style=\"color: #FFFFFF\">ปลุกเร้า: </span>ความเสียหายนี้ +1 และทำให้เกิด [Catalyzing Field] ที่จะทำให้ความเสียหายไม้/ไฟฟ้า 3 ครั้ง ถัดไป +1</p>",
                "icon_url": "https://upload-static.hoyoverse.com/hoyolab-wiki/2022/12/13/144837601/11ea6117480145a30b7893f1e8bd7115_4807853338317669663.png",
                "id": "talent10002",
                "key": "ความเสียหายไฟฟ้า",
                "materials": [],
                "points": [
                  {
                    "point_count": 0,
                    "point_type": ""
                  }
                ],
                "talent_img": "",
                "title": "ความเสียหายไฟฟ้า"
              },
              {
                "attributes": [],
                "desc": "<p><strong><span style=\"color: rgb(236, 229, 216)\">ความเสียหายกายภาพ</span></strong></p><p><span style=\"color: rgb(255, 255, 255)\">ความเสียหายกายภาพ</span><span style=\"color: rgba(255, 255, 255, 0.65)\">จะไม่ทำให้ติดสถานะธาตุและก็ไม่ทำให้เกิดปฏิกิริยาธาตุด้วย</span></p><p></p><p><strong><span style=\"color: #ECE5D8\">จำนวนเทิร์นต่อเนื่อง</span></strong></p><p>ในตอนจบเฟสของแต่ละเทิร์น<span style=\"color: #FFFFFF\"> จำนวนเทิร์นต่อเนื่อง</span>จะ -1; หลังจากที่ใช้<span style=\"color: #FFFFFF\">จำนวนเทิร์นต่อเนื่อง</span>จนหมดการ์ดใบนี้จะถูกทิ้งไป</p><p></p><p></p>",
                "icon_url": "https://upload-static.hoyoverse.com/hoyolab-wiki/2022/12/13/144837601/07bae546ac7c69ef6402170b283840c5_7711229881210329653.png",
                "id": "talent58442",
                "key": "รายละเอียดกติกา",
                "materials": [],
                "points": [
                  {
                    "point_count": 0,
                    "point_type": ""
                  }
                ],
                "talent_img": "",
                "title": "รายละเอียดกติกา"
              }
            ]
          }
        }
      ]
    },
    {
      "id": "49",
      "name": "แกลเลอรี",
      "components": [
        {
          "component_id": "gallery_character",
          "data": {
            "list": [
              {
                "id": "gallery_character28082",
                "img": "https://upload-static.hoyoverse.com/hoyolab-wiki/2022/12/22/144837601/7ec750fa7020893a8bcc4f3fcd9176bc_991999055091787186.gif",
                "imgDesc": "",
                "key": "ท่าไม้ตาย"
              },
              {
                "id": "gallery_character32715",
                "img": "https://upload-static.hoyoverse.com/hoyolab-wiki/2022/12/22/144837601/af65eb4951456b9bca902f1a0195ce08_2255677344704773251.png",
                "imgDesc": "",
                "key": "ไอคอนอวตาร"
              }
            ],
            "pic": ""
          }
        }
      ]
    },
    {
      "id": "50",
      "name": "เชิญตัวละคร ",
      "components": [
        {
          "component_id": "customize",
          "data": {
            "data": {
              "parsed_content": [
                {
                  "alignment": "center",
                  "content": [
                    {
                      "styles": [
                        "bold",
                        "color:rgb(255, 255, 255)"
                      ],
                      "text": "ปกไดนามิก",
                      "type": "text"
                    }
                  ],
                  "level": 1,
                  "type": "heading"
                },
                {
                  "content": [
                    {
                      "alignment": "center",
                      "type": "custom_image",
                      "url": "https://act-upload.hoyoverse.com/event-ugc-hoyowiki/2023/12/15/144837601/9f04425ead2744e2f17ae2dc0ccb8691_3648502336970407080.gif"
                    }
                  ],
                  "type": "paragraph"
                },
                {
                  "content": [
                    {
                      "styles": [
                        "bold",
                        "color:rgb(255, 255, 255)"
                      ],
                      "text": "ร้านขายการ์ด (",
                      "type": "text"
                    },
                    {
                      "amount": 1,
                      "display_style": "text",
                      "ep_id": 3329,
                      "icon_url": "https://upload-static.hoyoverse.com/hoyolab-wiki/2022/12/07/194600931/8f56ac468f468070eedc3fe87c96e392_2661412714891318875.png",
                      "name": "Prince",
                      "type": "custom_entry"
                    },
                    {
                      "styles": [
                        "bold",
                        "color:rgb(255, 255, 255)"
                      ],
                      "text": ")",
                      "type": "text"
                    }
                  ],
                  "level": 3,
                  "type": "heading"
                },
                {
                  "alignment": "center",
                  "content": [
                    {
                      "styles": [
                        "bold",
                        "color:rgb(255, 255, 255)"
                      ],
                      "text": "ไอเทม",
                      "type": "text"
                    }
                  ],
                  "type": "paragraph"
                },
                {
                  "alignment": "center",
                  "content": [
                    {
                      "styles": [
                        "bold",
                        "color:rgb(255, 255, 255)"
                      ],
                      "text": "ราคา",
                      "type": "text"
                    }
                  ],
                  "type": "paragraph"
                },
                {
                  "alignment": "center",
                  "content": [
                    {
                      "styles": [
                        "bold",
                        "color:rgb(255, 255, 255)"
                      ],
                      "text": "สต็อก",
                      "type": "text"
                    }
                  ],
                  "type": "paragraph"
                },
                {
                  "alignment": "center",
                  "content": [
                    {
                      "amount": 0,
                      "display_style": "card",
                      "ep_id": 3187,
                      "icon_url": "https://upload-static.hoyoverse.com/hoyolab-wiki/2022/12/02/144837601/31f1af14b97e8b36a6617bfa7f094abb_1112094279963317465.png",
                      "menu_id": 17,
                      "name": "Razor",
                      "type": "custom_entry"
                    }
                  ],
                  "type": "paragraph"
                },
                {
                  "alignment": "center",
                  "content": [
                    {
                      "amount": 4000,
                      "display_style": "card",
                      "ep_id": 3333,
                      "icon_url": "https://upload-static.hoyoverse.com/hoyolab-wiki/2022/12/08/77454259/c85bfab46d8c95659ab6dfb2e1629a87_2572904672223728374.png",
                      "name": "Lucky Coin",
                      "type": "custom_entry"
                    }
                  ],
                  "type": "paragraph"
                },
                {
                  "alignment": "center",
                  "content": [
                    {
                      "text": "1",
                      "type": "text"
                    }
                  ],
                  "type": "paragraph"
                },
                {
                  "content": [
                    {
                      "styles": [
                        "bold",
                        "color:rgb(255, 255, 255)"
                      ],
                      "text": "การดูเอลฉันมิตร",
                      "type": "text"
                    }
                  ],
                  "level": 3,
                  "type": "heading"
                },
                {
                  "content": [
                    {
                      "styles": [
                        "color:rgb(255, 215, 128)"
                      ],
                      "text": "แนะนำด่าน",
                      "type": "text"
                    }
                  ],
                  "type": "paragraph"
                },
                {
                  "content": [
                    {
                      "text": "\"การ์ด... ยุ่งยาก... แต่... สนุก...\"",
                      "type": "text"
                    }
                  ],
                  "type": "paragraph"
                },
                {
                  "content": [
                    {
                      "styles": [
                        "color:rgb(236, 229, 216)"
                      ],
                      "text": "[ข้อแนะนำ] เด็คของ Razor ประกอบด้วยการ์ดที่จะมอบ \"พลังงาน\" ให้แก่ \"Razor\" จำนวนมาก ซึ่งจะทำให้ Razor สามารถใช้ท่าไม้ตายได้เร็วยิ่งขึ้นและใช้รูปแบบการโจมตีที่รุนแรงหลังจากนั้นได้",
                      "type": "text"
                    }
                  ],
                  "type": "paragraph"
                },
                {
                  "content": [
                    {
                      "text": "ทีมของคู่ต่อสู้",
                      "type": "text"
                    }
                  ],
                  "type": "paragraph"
                },
                {
                  "content": [
                    {
                      "amount": 1,
                      "display_style": "card",
                      "ep_id": 3187,
                      "icon_url": "https://upload-static.hoyoverse.com/hoyolab-wiki/2022/12/02/144837601/31f1af14b97e8b36a6617bfa7f094abb_1112094279963317465.png",
                      "menu_id": 17,
                      "name": "Razor",
                      "type": "custom_entry"
                    },
                    {
                      "amount": 1,
                      "display_style": "card",
                      "ep_id": 3188,
                      "icon_url": "https://upload-static.hoyoverse.com/hoyolab-wiki/2022/12/02/144837601/a122204b72ab4c460887089b8e4664be_3120188744223111235.png",
                      "menu_id": 17,
                      "name": "Fischl",
                      "type": "custom_entry"
                    },
                    {
                      "amount": 1,
                      "display_style": "card",
                      "ep_id": 3176,
                      "icon_url": "https://upload-static.hoyoverse.com/hoyolab-wiki/2022/12/02/144837601/bffac6cdb7bf11846a00283924b7b617_6424248644745131986.png",
                      "menu_id": 17,
                      "name": "Chongyun",
                      "type": "custom_entry"
                    }
                  ],
                  "type": "paragraph"
                },
                {
                  "content": [
                    {
                      "styles": [
                        "bold",
                        "color:rgb(255, 255, 255)"
                      ],
                      "text": "เป้าหมายการท้าทาย",
                      "type": "text"
                    }
                  ],
                  "level": 3,
                  "type": "heading"
                },
                {
                  "content": [
                    {
                      "styles": [
                        "bold",
                        "color:rgb(255, 255, 255)"
                      ],
                      "text": "รางวัล",
                      "type": "text"
                    }
                  ],
                  "level": 3,
                  "type": "heading"
                },
                {
                  "content": [
                    {
                      "text": "ได้รับชัยชนะ",
                      "type": "text"
                    }
                  ],
                  "type": "paragraph"
                },
                {
                  "content": [
                    {
                      "amount": 1,
                      "display_style": "card",
                      "ep_id": 3187,
                      "icon_url": "https://upload-static.hoyoverse.com/hoyolab-wiki/2022/12/02/144837601/31f1af14b97e8b36a6617bfa7f094abb_1112094279963317465.png",
                      "menu_id": 17,
                      "name": "Razor",
                      "type": "custom_entry"
                    }
                  ],
                  "type": "paragraph"
                },
                {
                  "content": [
                    {
                      "text": "ได้รับชัยชนะภายใน 6 เทิร์น",
                      "type": "text"
                    }
                  ],
                  "type": "paragraph"
                },
                {
                  "content": [
                    {
                      "amount": 1,
                      "display_style": "card",
                      "ep_id": 3226,
                      "icon_url": "https://upload-static.hoyoverse.com/hoyolab-wiki/2022/12/02/144837601/c5cee39d24207d15ed0383b971e8afed_769971483047454770.png",
                      "menu_id": 18,
                      "name": "Awakening",
                      "type": "custom_entry"
                    }
                  ],
                  "type": "paragraph"
                },
                {
                  "content": [
                    {
                      "text": "ชนะโดยจำนวนตัวละครที่ถูกกำจัดต่ำกว่า 2 ตัว",
                      "type": "text"
                    }
                  ],
                  "type": "paragraph"
                },
                {
                  "content": [
                    {
                      "amount": 1,
                      "display_style": "card",
                      "ep_id": 3226,
                      "icon_url": "https://upload-static.hoyoverse.com/hoyolab-wiki/2022/12/02/144837601/c5cee39d24207d15ed0383b971e8afed_769971483047454770.png",
                      "menu_id": 18,
                      "name": "Awakening",
                      "type": "custom_entry"
                    }
                  ],
                  "type": "paragraph"
                },
                {
                  "content": [
                    {
                      "styles": [
                        "bold",
                        "color:rgb(255, 255, 255)"
                      ],
                      "text": "การต่อสู้อย่างจริงจัง",
                      "type": "text"
                    }
                  ],
                  "level": 3,
                  "type": "heading"
                },
                {
                  "content": [
                    {
                      "styles": [
                        "color:rgb(255, 215, 128)"
                      ],
                      "text": "แนะนำด่าน",
                      "type": "text"
                    }
                  ],
                  "type": "paragraph"
                },
                {
                  "content": [
                    {
                      "text": "\"การ์ด... ไม่เข้าใจ... แต่ฉัน... ต้องชนะ!\"",
                      "type": "text"
                    }
                  ],
                  "type": "paragraph"
                },
                {
                  "content": [
                    {
                      "styles": [
                        "color:rgb(236, 229, 216)"
                      ],
                      "text": "[กฎพิเศษ] ในตอนเริ่ม \"Razor\" จะติดตั้งการ์ดพรสวรรค์ \"Awakening\"",
                      "type": "text"
                    }
                  ],
                  "type": "paragraph"
                },
                {
                  "content": [
                    {
                      "text": "ทีมของคู่ต่อสู้",
                      "type": "text"
                    }
                  ],
                  "type": "paragraph"
                },
                {
                  "content": [
                    {
                      "amount": 1,
                      "display_style": "card",
                      "ep_id": 3187,
                      "icon_url": "https://upload-static.hoyoverse.com/hoyolab-wiki/2022/12/02/144837601/31f1af14b97e8b36a6617bfa7f094abb_1112094279963317465.png",
                      "menu_id": 17,
                      "name": "Razor",
                      "type": "custom_entry"
                    },
                    {
                      "amount": 1,
                      "display_style": "card",
                      "ep_id": 3188,
                      "icon_url": "https://upload-static.hoyoverse.com/hoyolab-wiki/2022/12/02/144837601/a122204b72ab4c460887089b8e4664be_3120188744223111235.png",
                      "menu_id": 17,
                      "name": "Fischl",
                      "type": "custom_entry"
                    },
                    {
                      "amount": 1,
                      "display_style": "card",
                      "ep_id": 3176,
                      "icon_url": "https://upload-static.hoyoverse.com/hoyolab-wiki/2022/12/02/144837601/bffac6cdb7bf11846a00283924b7b617_6424248644745131986.png",
                      "menu_id": 17,
                      "name": "Chongyun",
                      "type": "custom_entry"
                    }
                  ],
                  "type": "paragraph"
                },
                {
                  "content": [
                    {
                      "text": "ปลดล็อกหลัง:",
                      "type": "text"
                    }
                  ],
                  "type": "paragraph"
                },
                {
                  "content": [
                    {
                      "text": "มีเลเวลผู้เล่นถึง 7",
                      "type": "text"
                    }
                  ],
                  "type": "paragraph"
                },
                {
                  "content": [
                    {
                      "text": "สำเร็จเป้าหมายการท้าทาย Razor - เป็นมิตร 3 อัน",
                      "type": "text"
                    }
                  ],
                  "type": "paragraph"
                },
                {
                  "content": [
                    {
                      "styles": [
                        "bold",
                        "color:rgb(255, 255, 255)"
                      ],
                      "text": "เป้าหมายการท้าทาย",
                      "type": "text"
                    }
                  ],
                  "level": 3,
                  "type": "heading"
                },
                {
                  "content": [
                    {
                      "styles": [
                        "bold",
                        "color:rgb(255, 255, 255)"
                      ],
                      "text": "รางวัล",
                      "type": "text"
                    }
                  ],
                  "level": 3,
                  "type": "heading"
                },
                {
                  "content": [
                    {
                      "text": "ได้รับชัยชนะ",
                      "type": "text"
                    }
                  ],
                  "type": "paragraph"
                },
                {
                  "content": [
                    {
                      "text": "1000x",
                      "type": "text"
                    },
                    {
                      "amount": 1,
                      "display_style": "text",
                      "ep_id": 3333,
                      "icon_url": "",
                      "name": "เหรียญนําโชค",
                      "type": "custom_entry"
                    }
                  ],
                  "type": "paragraph"
                },
                {
                  "content": [
                    {
                      "styles": [
                        "bold",
                        "color:rgb(255, 255, 255)"
                      ],
                      "text": "แขกที่มาท้าทาย: Razor",
                      "type": "text"
                    }
                  ],
                  "level": 3,
                  "type": "heading"
                },
                {
                  "content": [
                    {
                      "styles": [
                        "color:rgb(255, 215, 128)"
                      ],
                      "text": "แนะนำด่าน",
                      "type": "text"
                    }
                  ],
                  "type": "paragraph"
                },
                {
                  "content": [
                    {
                      "text": "\"การ์ด... ยุ่งยาก... แต่... สนุก...\"",
                      "type": "text"
                    }
                  ],
                  "type": "paragraph"
                },
                {
                  "content": [
                    {
                      "styles": [
                        "color:rgb(236, 229, 216)"
                      ],
                      "text": "[ข้อแนะนำ] เด็คของ Razor ประกอบด้วยการ์ดที่จะมอบ \"พลังงาน\" ให้แก่ \"Razor\" จำนวนมาก ซึ่งจะทำให้ Razor สามารถใช้ท่าไม้ตายได้เร็วยิ่งขึ้นและใช้รูปแบบการโจมตีที่รุนแรงหลังจากนั้นได้",
                      "type": "text"
                    }
                  ],
                  "type": "paragraph"
                },
                {
                  "content": [
                    {
                      "text": "ทีมของคู่ต่อสู้",
                      "type": "text"
                    }
                  ],
                  "type": "paragraph"
                },
                {
                  "content": [
                    {
                      "amount": 1,
                      "display_style": "card",
                      "ep_id": 3187,
                      "icon_url": "https://upload-static.hoyoverse.com/hoyolab-wiki/2022/12/02/144837601/31f1af14b97e8b36a6617bfa7f094abb_1112094279963317465.png",
                      "menu_id": 17,
                      "name": "Razor",
                      "type": "custom_entry"
                    },
                    {
                      "amount": 1,
                      "display_style": "card",
                      "ep_id": 3188,
                      "icon_url": "https://upload-static.hoyoverse.com/hoyolab-wiki/2022/12/02/144837601/a122204b72ab4c460887089b8e4664be_3120188744223111235.png",
                      "menu_id": 17,
                      "name": "Fischl",
                      "type": "custom_entry"
                    },
                    {
                      "amount": 1,
                      "display_style": "card",
                      "ep_id": 3176,
                      "icon_url": "https://upload-static.hoyoverse.com/hoyolab-wiki/2022/12/02/144837601/bffac6cdb7bf11846a00283924b7b617_6424248644745131986.png",
                      "menu_id": 17,
                      "name": "Chongyun",
                      "type": "custom_entry"
                    }
                  ],
                  "type": "paragraph"
                },
                {
                  "alignment": "center",
                  "content": [
                    {
                      "styles": [
                        "bold",
                        "color:rgb(255, 255, 255)"
                      ],
                      "text": "เลเวลผู้เล่น",
                      "type": "text"
                    }
                  ],
                  "level": 3,
                  "type": "heading"
                },
                {
                  "alignment": "center",
                  "content": [
                    {
                      "styles": [
                        "bold",
                        "color:rgb(255, 255, 255)"
                      ],
                      "text": "รางวัล",
                      "type": "text"
                    }
                  ],
                  "level": 3,
                  "type": "heading"
                },
                {
                  "alignment": "center",
                  "content": [
                    {
                      "styles": [
                        "color:rgb(236, 229, 216)"
                      ],
                      "text": "2",
                      "type": "text"
                    }
                  ],
                  "type": "paragraph"
                },
                {
                  "alignment": "center",
                  "content": [
                    {
                      "amount": 200,
                      "display_style": "card",
                      "ep_id": 3816,
                      "icon_url": "https://upload-static.hoyoverse.com/hoyolab-wiki/2023/05/27/77454259/a3dfc591cecc908ea00f31c9a3de083f_9193765536653033097.png",
                      "name": "Player EXP",
                      "type": "custom_entry"
                    },
                    {
                      "amount": 300,
                      "display_style": "card",
                      "ep_id": 3333,
                      "icon_url": "https://upload-static.hoyoverse.com/hoyolab-wiki/2022/12/08/77454259/c85bfab46d8c95659ab6dfb2e1629a87_2572904672223728374.png",
                      "name": "Lucky Coin",
                      "type": "custom_entry"
                    }
                  ],
                  "type": "paragraph"
                },
                {
                  "alignment": "center",
                  "content": [
                    {
                      "styles": [
                        "color:rgb(236, 229, 216)"
                      ],
                      "text": "3 - 4",
                      "type": "text"
                    }
                  ],
                  "type": "paragraph"
                },
                {
                  "alignment": "center",
                  "content": [
                    {
                      "amount": 200,
                      "display_style": "card",
                      "ep_id": 3816,
                      "icon_url": "https://upload-static.hoyoverse.com/hoyolab-wiki/2023/05/27/77454259/a3dfc591cecc908ea00f31c9a3de083f_9193765536653033097.png",
                      "name": "Player EXP",
                      "type": "custom_entry"
                    },
                    {
                      "amount": 600,
                      "display_style": "card",
                      "ep_id": 3333,
                      "icon_url": "https://upload-static.hoyoverse.com/hoyolab-wiki/2022/12/08/77454259/c85bfab46d8c95659ab6dfb2e1629a87_2572904672223728374.png",
                      "name": "Lucky Coin",
                      "type": "custom_entry"
                    }
                  ],
                  "type": "paragraph"
                },
                {
                  "alignment": "center",
                  "content": [
                    {
                      "styles": [
                        "color:rgb(236, 229, 216)"
                      ],
                      "text": "5 - 6",
                      "type": "text"
                    }
                  ],
                  "type": "paragraph"
                },
                {
                  "alignment": "center",
                  "content": [
                    {
                      "amount": 200,
                      "display_style": "card",
                      "ep_id": 3816,
                      "icon_url": "https://upload-static.hoyoverse.com/hoyolab-wiki/2023/05/27/77454259/a3dfc591cecc908ea00f31c9a3de083f_9193765536653033097.png",
                      "name": "Player EXP",
                      "type": "custom_entry"
                    },
                    {
                      "amount": 900,
                      "display_style": "card",
                      "ep_id": 3333,
                      "icon_url": "https://upload-static.hoyoverse.com/hoyolab-wiki/2022/12/08/77454259/c85bfab46d8c95659ab6dfb2e1629a87_2572904672223728374.png",
                      "name": "Lucky Coin",
                      "type": "custom_entry"
                    }
                  ],
                  "type": "paragraph"
                },
                {
                  "alignment": "center",
                  "content": [
                    {
                      "styles": [
                        "color:rgb(236, 229, 216)"
                      ],
                      "text": "7 - 9",
                      "type": "text"
                    }
                  ],
                  "type": "paragraph"
                },
                {
                  "alignment": "center",
                  "content": [
                    {
                      "amount": 200,
                      "display_style": "card",
                      "ep_id": 3816,
                      "icon_url": "https://upload-static.hoyoverse.com/hoyolab-wiki/2023/05/27/77454259/a3dfc591cecc908ea00f31c9a3de083f_9193765536653033097.png",
                      "name": "Player EXP",
                      "type": "custom_entry"
                    },
                    {
                      "amount": 1200,
                      "display_style": "card",
                      "ep_id": 3333,
                      "icon_url": "https://upload-static.hoyoverse.com/hoyolab-wiki/2022/12/08/77454259/c85bfab46d8c95659ab6dfb2e1629a87_2572904672223728374.png",
                      "name": "Lucky Coin",
                      "type": "custom_entry"
                    }
                  ],
                  "type": "paragraph"
                },
                {
                  "alignment": "center",
                  "content": [
                    {
                      "styles": [
                        "color:rgb(236, 229, 216)"
                      ],
                      "text": "10",
                      "type": "text"
                    }
                  ],
                  "type": "paragraph"
                },
                {
                  "alignment": "center",
                  "content": [
                    {
                      "amount": 200,
                      "display_style": "card",
                      "ep_id": 3816,
                      "icon_url": "https://upload-static.hoyoverse.com/hoyolab-wiki/2023/05/27/77454259/a3dfc591cecc908ea00f31c9a3de083f_9193765536653033097.png",
                      "name": "Player EXP",
                      "type": "custom_entry"
                    },
                    {
                      "amount": 1500,
                      "display_style": "card",
                      "ep_id": 3333,
                      "icon_url": "https://upload-static.hoyoverse.com/hoyolab-wiki/2022/12/08/77454259/c85bfab46d8c95659ab6dfb2e1629a87_2572904672223728374.png",
                      "name": "Lucky Coin",
                      "type": "custom_entry"
                    }
                  ],
                  "type": "paragraph"
                }
              ]
            }
          }
        }
      ]
    }
  ],
  "filter_values": {
    "card_character_weapon_type": [
      "ดาบใหญ่"
    ],
    "card_character_charging_point": [
      "พลังงาน: 3"
    ],
    "card_character_obtaining_method": [
      "เชิญตัวละคร"
    ],
    "card_character_camp": [
      "Mondstadt"
    ],
    "card_character_element": [
      "ธาตุไฟฟ้า"
    ]
  },
  "menu_id": 17,
  "menu_name": "การ์ดตัวละคร",
  "version": 1702641983
}